pypubfigs/__init__.py
pypubfigs/palettes.py
pypubfigs/themes.py
pypubfigs/version.py
pypubfigs-0.1.3.dist-info/licenses/LICENSE.md
pypubfigs-0.1.3.dist-info/METADATA
pypubfigs-0.1.3.dist-info/WHEEL
pypubfigs-0.1.3.dist-info/top_level.txt
pypubfigs-0.1.3.dist-info/RECORD
