Metadata-Version: 2.4
Name: pypubfigs
Version: 0.1.3
Summary: Colorblind-friendly color palettes and themes for publication-quality scientific figures using matplotlib and seaborn.
Home-page: https://github.com/jlsteenwyk/pypubfigs
Author: Jacob L. Steenwyk
Author-email: jlsteenwyk@gmail.com
Classifier: Operating System :: OS Independent
Classifier: Intended Audience :: Science/Research
Classifier: Programming Language :: Python
Classifier: Programming Language :: Python :: 3.9
Classifier: Programming Language :: Python :: 3.10
Classifier: Programming Language :: Python :: 3.11
Classifier: Programming Language :: Python :: 3.12
Classifier: Programming Language :: Python :: 3.13
Classifier: Topic :: Scientific/Engineering
Requires-Python: >=3.8
License-File: LICENSE.md
Requires-Dist: seaborn>=0.12.2
Requires-Dist: matplotlib>=3.7.0
Dynamic: author
Dynamic: author-email
Dynamic: classifier
Dynamic: description
Dynamic: description-content-type
Dynamic: home-page
Dynamic: license-file
Dynamic: requires-dist
Dynamic: requires-python
Dynamic: summary
